glam/__init__.py
glam/app.py
glam/app_conf.py
glam/interface/__init__.py
glam/interface/_geocoder.py
glam/matching/__init__.py
glam/matching/_base_matcher.py
glam/matching/_linz.py
glam/matching/_siamese.py
glam/matching/embedded/_embedded_matcher.py
glam/matching/embedded/_linz.py
glam/matching/embedded/_model.py
glam/matching/embedded/_predict.py
glam/matching/fuzzy/_fuzzy_matcher.py
glam/matching/fuzzy/_linz.py
glam/matching/fuzzy/_predict.py
glam/matching/hybrid/_hybrid_matcher.py
glam/matching/siamese/_dataset.py
glam/matching/siamese/_predict.py
glam/matching/siamese/_siamese_matcher.py
glam/matching/siamese/_siamese_model.py
glam/matching/siamese/_train.py
glam/matching/siamese/default_model/keras_metadata.pb
glam/matching/siamese/default_model/saved_model.pb
glam/matching/siamese/default_model/variables/variables.data-00000-of-00001
glam/matching/siamese/default_model/variables/variables.index
glam/matching/siamese_labels/_dataset.py
glam/matching/tfidf/_predict.py
glam/matching/tfidf/_tfidf_matcher.py
glam/parsing/__init__.py
glam/parsing/_base_parser.py
glam/parsing/_dataset.py
glam/parsing/_linz.py
glam/parsing/_predict.py
glam/parsing/_train.py
glam/parsing/hmm/_hmm_model.py
glam/parsing/hmm/_hmm_parser.py
glam/parsing/rnn/_rnn_model.py
glam/parsing/rnn/_rnn_parser.py
glam/parsing/rnn/default_model/keras_metadata.pb
glam/parsing/rnn/default_model/saved_model.pb
glam/parsing/rnn/default_model/variables/variables.data-00000-of-00001
glam/parsing/rnn/default_model/variables/variables.index
glam/parsing/rnn/other_model/keras_metadata.pb
glam/parsing/rnn/other_model/saved_model.pb
glam/parsing/rnn/other_model/variables/variables.data-00000-of-00001
glam/parsing/rnn/other_model/variables/variables.index
glam/preprocessing/__init__.py
glam/preprocessing/_preprocessing.py
glam/preprocessing/_preprocessor.py
glam/utils/ModelWithGrad.py
glam/utils/__init__.py
glam/utils/lookups.py
glam/utils/tqdm_predict_callback.py
glam/utils/typo.py
glam/utils/utils.py
GLAM-0.3.7.dist-info/LICENSE
GLAM-0.3.7.dist-info/METADATA
GLAM-0.3.7.dist-info/WHEEL
GLAM-0.3.7.dist-info/top_level.txt
GLAM-0.3.7.dist-info/zip-safe
GLAM-0.3.7.dist-info/RECORD
